ftai-1.0.0.dist-info/licenses/LICENSE
ftai_linter/__init__.py
ftai_linter/cli.py
ftai_linter/linter.py
ftai-1.0.0.dist-info/METADATA
ftai-1.0.0.dist-info/WHEEL
ftai-1.0.0.dist-info/entry_points.txt
ftai-1.0.0.dist-info/top_level.txt
ftai-1.0.0.dist-info/RECORD
