Metadata-Version: 2.4
Name: ftai
Version: 1.0.0
Summary: FTAI CLI tool for linting, formatting, and converting .ftai files.
Author-email: Michael Folk <michael.folk@folktechai.com>
License: Apache-2.0
Project-URL: Homepage, https://github.com/FolkTechAI/ftai-spec
Project-URL: Repository, https://github.com/FolkTechAI/ftai-spec
Project-URL: Documentation, https://github.com/FolkTechAI/ftai-spec#readme
Keywords: ftai,ai,linter,format,human-ai,agent
Classifier: Development Status :: 3 - Alpha
Classifier: Intended Audience :: Developers
Classifier: License :: OSI Approved :: Apache Software License
Classifier: Programming Language :: Python :: 3
Classifier: Programming Language :: Python :: 3.8
Classifier: Programming Language :: Python :: 3.9
Classifier: Programming Language :: Python :: 3.10
Classifier: Programming Language :: Python :: 3.11
Classifier: Programming Language :: Python :: 3.12
Classifier: Topic :: Software Development :: Libraries :: Python Modules
Classifier: Topic :: Text Processing :: Markup
Requires-Python: >=3.8
License-File: LICENSE
Dynamic: license-file
